utils/ReadFrameData.py
utils/canvas_model.py
utils/common_component.py
utils/const.py
utils/csvHelper.py
utils/cv_model.py
utils/cv_util.py
utils/math_util.py
utils/normarlize.py
utils/poseMeasure.py
utils/poseMeasureFormat.py
utils/pose_util.py
utils/qt_component.py
utils/qt_model.py
utils/version.py
poseutil-0.7.4.dist-info/METADATA
poseutil-0.7.4.dist-info/WHEEL
poseutil-0.7.4.dist-info/top_level.txt
poseutil-0.7.4.dist-info/RECORD
