Metadata-Version: 2.1
Name: poseutil
Version: 0.7.4
Summary: pose engine utils
Home-page: 
Author: jyj902
Author-email: jyj902@naver.com
Classifier: Programming Language :: Python :: 3.6
Classifier: Programming Language :: Python :: 3.7
Classifier: Programming Language :: Python :: 3.8
Classifier: Programming Language :: Python :: 3.9
Classifier: Programming Language :: Python :: 3.10
Classifier: Programming Language :: Python :: 3.11
Requires: sklearn
Requires: pandas
Requires: numpy
Requires: cv2
Requires: pickle
Requires: pyqt6
Requires-Python: >=3.6
